alphawave/AlphaWave.py
alphawave/ChoiceResponseValidator.py
alphawave/Colorize.py
alphawave/DefaultResponseValidator.py
alphawave/JSONResponseValidator.py
alphawave/MemoryFork.py
alphawave/OSClient.py
alphawave/OpenAIClient.py
alphawave/PythonResponseValidator.py
alphawave/RepairTestClient.py
alphawave/Response.py
alphawave/TOMLResponseValidator.py
alphawave/TestClient.py
alphawave/TestClientTest.py
alphawave/__init__.py
alphawave/alphawaveTypes.py
alphawave/chat.py
alphawave/internalTypes.py
alphawave/jsonParser.py
alphawave_agents/Agent.py
alphawave_agents/AgentCommandSection.py
alphawave_agents/AgentCommandValidator.py
alphawave_agents/AskCommand.py
alphawave_agents/CompleteTaskCommand.py
alphawave_agents/ConfirmAnswerCommand.py
alphawave_agents/FinalAnswerCommand.py
alphawave_agents/MathCommand.py
alphawave_agents/PromptCommand.py
alphawave_agents/SchemaBasedCommand.py
alphawave_agents/SentimentAnalysis.py
alphawave_agents/SetPropertyCommand.py
alphawave_agents/__init__.py
alphawave_agents/agentTypes.py
alphawave_pyexts/FsInference.py
alphawave_pyexts/LLMClient.py
alphawave_pyexts/SearchCommand.py
alphawave_pyexts/agentChat.py
alphawave_pyexts/chat.py
alphawave_pyexts/chatglm2.py
alphawave_pyexts/configuration_RW.py
alphawave_pyexts/conversation.py
alphawave_pyexts/falcon7.py
alphawave_pyexts/handler.py
alphawave_pyexts/llama-2-13b-chat.py
alphawave_pyexts/llama-2-70b-chat.py
alphawave_pyexts/llama-2-70b.py
alphawave_pyexts/modelling_RW.py
alphawave_pyexts/serverUtils.py
alphawave_pyexts/utilityV2.py
alphawave_pyexts/vicuna13.py
alphawave_pyexts/vicuna7.py
alphawave_pyexts/wvicuna30.py
alphawave_pyexts/llmsearch/google_search_concurrent.py
alphawave_pyexts/llmsearch/search_service.py
alphawave-0.4.1.dist-info/LICENSE
alphawave-0.4.1.dist-info/METADATA
alphawave-0.4.1.dist-info/WHEEL
alphawave-0.4.1.dist-info/top_level.txt
alphawave-0.4.1.dist-info/RECORD
