Metadata-Version: 2.1
Name: alphawave
Version: 0.4.1
Summary: AlphaWave-py - Functions for smaller Large Language Models (sLLMs)
Author-email: Steven Ickman <author@example.com>, Bruce DAmbrosio <bruce.dambrosio@gmail.com>
Project-URL: Homepage, https://tuuyi.io/alphawave
Project-URL: Bug Tracker, https://github.com/Stevenic/alphawave-py/issues
Classifier: Programming Language :: Python :: 3
Classifier: License :: OSI Approved :: MIT License
Classifier: Operating System :: OS Independent
Requires-Python: >=3.8
License-File: LICENSE
Requires-Dist: promptrix
Requires-Dist: accelerate
Requires-Dist: aiounittest
Requires-Dist: cerberus
Requires-Dist: openai
Requires-Dist: nltk
Requires-Dist: pylint
Requires-Dist: pyyaml
Requires-Dist: pyee
Requires-Dist: selenium
Requires-Dist: termcolor
Requires-Dist: requests
Requires-Dist: tiktoken
Requires-Dist: toml
Requires-Dist: wordfreq
Requires-Dist: tenacity
Requires-Dist: transformers
Requires-Dist: torch
Requires-Dist: jsonschema
Requires-Dist: importlib-metadata ; python_version < "3.9"
